canonical_sets/__init__.py
canonical_sets/data/__init__.py
canonical_sets/data/adult.py
canonical_sets/data/base.py
canonical_sets/data/compas.py
canonical_sets/gan/__init__.py
canonical_sets/gan/lucidgan.py
canonical_sets/gan/sampler.py
canonical_sets/group.py
canonical_sets/lucid.py
canonical_sets/models/__init__.py
canonical_sets/models/classifiers.py
canonical_sets/utils.py
canonical_sets-0.0.3.dist-info/LICENSE
canonical_sets-0.0.3.dist-info/WHEEL
canonical_sets-0.0.3.dist-info/METADATA
canonical_sets-0.0.3.dist-info/RECORD
