Metadata-Version: 2.1
Name: canonical-sets
Version: 0.0.3
Summary: Exposing Algorithmic Bias with Canonical Sets.
Home-page: https://data.research.vub.be/
License: MIT
Keywords: fairness,bias,inverse design,generative models,interpretability,python
Author: Integrated Intelligence Lab
Maintainer: Andres Algaba
Maintainer-email: andres.algaba@vub.be
Requires-Python: >=3.8,<3.11
Classifier: License :: OSI Approved :: MIT License
Classifier: Programming Language :: Python :: 3
Classifier: Programming Language :: Python :: 3.10
Classifier: Programming Language :: Python :: 3.8
Classifier: Programming Language :: Python :: 3.9
Requires-Dist: ctgan (>=0.7.0)
Requires-Dist: matplotlib (>=3.5.2)
Requires-Dist: numpy (>=1.22)
Requires-Dist: pandas (>=1.4.2)
Requires-Dist: scikit-learn (>=1.1.1)
Requires-Dist: scipy (>=1.9.0)
Requires-Dist: seaborn (>=0.12.0)
Requires-Dist: tensorflow (>=2.9.1,<2.11); sys_platform != "darwin"
Requires-Dist: tensorflow (>=2.9.1,<2.11); sys_platform == "darwin" and platform_machine == "x86_64"
Requires-Dist: tensorflow-macos (>=2.9.1,<2.11); sys_platform == "darwin" and platform_machine == "arm64"
Requires-Dist: torch (>=1.11.0)
Requires-Dist: tqdm (>=4.64.0)
Project-URL: Repository, https://github.com/Integrated-Intelligence-Lab/canonical_sets
